aeon/__init__.py
aeon/__main__.py
aeon/backend/__init__.py
aeon/backend/evaluator.py
aeon/bindings/__init__.py
aeon/bindings/binding_utils.py
aeon/bindings/image.py
aeon/bindings/learning.py
aeon/bindings/table.py
aeon/core/__init__.py
aeon/core/bind.py
aeon/core/distance.py
aeon/core/equality.py
aeon/core/instantiation.py
aeon/core/liquid.py
aeon/core/liquid_ops.py
aeon/core/pprint.py
aeon/core/substitutions.py
aeon/core/terms.py
aeon/core/types.py
aeon/decorators/__init__.py
aeon/decorators/api.py
aeon/elaboration/__init__.py
aeon/elaboration/context.py
aeon/elaboration/instantiation.py
aeon/facade/__init__.py
aeon/facade/api.py
aeon/facade/driver.py
aeon/frontend/__init__.py
aeon/frontend/aeon_core.lark
aeon/frontend/anf_converter.py
aeon/frontend/parser.py
aeon/locations/__init__.py
aeon/logger/__init__.py
aeon/logger/logger.py
aeon/lsp/__init__.py
aeon/lsp/aeon_adapter.py
aeon/lsp/server.py
aeon/optimization/__init__.py
aeon/optimization/normal_form.py
aeon/prelude/__init__.py
aeon/prelude/prelude.py
aeon/sugar/__init__.py
aeon/sugar/aeon_sugar.lark
aeon/sugar/ast_helpers.py
aeon/sugar/bind.py
aeon/sugar/desugar.py
aeon/sugar/equality.py
aeon/sugar/lifting.py
aeon/sugar/lowering.py
aeon/sugar/parser.py
aeon/sugar/program.py
aeon/sugar/stypes.py
aeon/sugar/substitutions.py
aeon/synthesis/__init__.py
aeon/synthesis/api.py
aeon/synthesis/decorators.py
aeon/synthesis/entrypoint.py
aeon/synthesis/fitness.py
aeon/synthesis/identification.py
aeon/synthesis/grammar/bounds.py
aeon/synthesis/grammar/ge_synthesis.py
aeon/synthesis/grammar/grammar_generation.py
aeon/synthesis/grammar/mangling.py
aeon/synthesis/grammar/refinements.py
aeon/synthesis/grammar/utils.py
aeon/synthesis/modules/synthesizerfactory.py
aeon/synthesis/modules/llm/__init__.py
aeon/synthesis/modules/synquid/build.py
aeon/synthesis/modules/synquid/synthesizer.py
aeon/synthesis/uis/api.py
aeon/synthesis/uis/terminal.py
aeon/typechecking/__init__.py
aeon/typechecking/context.py
aeonlang-4.0.2b0.dist-info/METADATA
aeonlang-4.0.2b0.dist-info/WHEEL
aeonlang-4.0.2b0.dist-info/entry_points.txt
aeonlang-4.0.2b0.dist-info/top_level.txt
aeonlang-4.0.2b0.dist-info/RECORD
