Metadata-Version: 2.4
Name: AeonLang
Version: 4.0.2b0
Summary: Language with Refinement Types
Author-email: Alcides Fonseca <me@alcidesfonseca.com>
License: https://opensource.org/licenses/MIT
Project-URL: homepage, https://github.com/alcides/aeon
Project-URL: repository, https://github.com/alcides/aeon
Project-URL: documentation, https://github.com/alcides/aeon
Keywords: programming language, liquid types
Classifier: Development Status :: 4 - Beta
Classifier: Programming Language :: Python :: 3.10
Classifier: Programming Language :: Python :: 3.11
Classifier: Programming Language :: Python :: 3.12
Classifier: Programming Language :: Python :: 3.13
Requires-Python: <4,>3.10
Requires-Dist: argparse
Requires-Dist: configparser
Requires-Dist: lark
Requires-Dist: loguru
Requires-Dist: geneticengine==0.8.10
Requires-Dist: multiprocess
Requires-Dist: numpy
Requires-Dist: ollama
Requires-Dist: pathos
Requires-Dist: pillow
Requires-Dist: psb2
Requires-Dist: pydantic==2.12.3
Requires-Dist: pygls==1.3.1
Requires-Dist: pytest
Requires-Dist: requests
Requires-Dist: types-requests
Requires-Dist: scikit-image
Requires-Dist: sympy
Requires-Dist: textdistance
Requires-Dist: z3-solver>=4
Requires-Dist: zstandard==0.25.0
Requires-Dist: zss
Provides-Extra: tests
Requires-Dist: pytest; extra == "tests"
Requires-Dist: pytest-beartype; extra == "tests"
